{
  "generated_utc": "2026-02-20T04:12:54.466703",
  "ticker": "BTC-USD",
  "train_window_days": 365,
  "test_window_days": 28,
  "lockbox_pct": 0.15,
  "indicator_config": {
    "trend_min": 2,
    "sig_ema_fast_on": true,
    "sig_ema_slow_on": true,
    "sig_macd_on": true,
    "sig_roc_on": true,
    "sig_pbull_slope_on": true,
    "strength_min": 0,
    "participation_min": 0,
    "sig_adx_on": false,
    "sig_volume_on": false,
    "risk_min": 2,
    "sig_rsi_on": true,
    "sig_volatility_on": true,
    "sig_momentum_on": true,
    "sig_confidence_on": true,
    "p_bull_min": 0.55,
    "stress_range_threshold": 0.04,
    "rsi_max": 90,
    "momentum_min_pct": 1.0,
    "volatility_max_pct": 80.0,
    "adx_min": 25,
    "rsi_period": 14,
    "momentum_period": 5,
    "volume_sma_period": 10,
    "volatility_period": 24,
    "adx_period": 14,
    "atr_period": 14,
    "ema_fast": 20,
    "ema_slow": 50,
    "roc_period": 8,
    "p_bull_slope_period": 3,
    "macd_fast": 12,
    "macd_slow": 26,
    "macd_signal": 9
  },
  "risk_config": {
    "stop_loss_pct": -2.5,
    "take_profit_pct": 4.0,
    "min_regime_bars": 2,
    "regime_flip_grace_bars": 2,
    "use_pbull_sizing": true,
    "fee_bps": 5,
    "slippage_bps": 3,
    "use_atr_stops": false,
    "k_stop": 2.0,
    "k_tp": 3.0,
    "use_trailing_stop": true,
    "trail_atr_mult": 2.5,
    "trail_activation_pct": 1.5,
    "trailing_stop_pct": 2.0,
    "kill_switch_enabled": true,
    "kill_switch_dd_pct": 9.0,
    "kill_switch_cooldown_h": 24,
    "use_market_quality_filter": true,
    "stress_force_flat": true,
    "stress_range_threshold": 0.04,
    "stress_cooldown_hours": 24,
    "use_vol_targeting": false,
    "vol_target_pct": 30.0,
    "vol_target_min_mult": 0.25,
    "vol_target_max_mult": 1.0
  },
  "config_hash": "2e9e399f",
  "execution_rule_version": "v1_next_open",
  "n_folds": 7,
  "fold_metrics": [
    {
      "Fold": 1,
      "Train Start": "2024-04-20",
      "Train End": "2025-04-20",
      "Test Start": "2025-04-20",
      "Test End": "2025-05-18",
      "_train_end_ts": "2025-04-20 00:00:00+00:00",
      "_test_start_ts": "2025-04-20 01:00:00+00:00",
      "Trades": 9,
      "Total Return (%)": 10.95,
      "Win Rate (%)": 66.67,
      "Max Drawdown (%)": -3.68,
      "Sharpe Ratio": 5.261,
      "Total Fees ($)": 91.02,
      "attribution": {
        "bars_bull_regime": 352,
        "bars_signal_ok_while_bull": 243,
        "bars_eligible": 197,
        "entries_blocked_cooldown": 6,
        "entries_blocked_gate": 0,
        "entries_blocked_external": 0,
        "exits_stop_loss": 0,
        "exits_trailing_stop": 3,
        "exits_take_profit": 2,
        "exits_regime_flip": 4,
        "exits_end_of_data": 0,
        "exits_force_flat": 0,
        "exits_kill_switch": 0,
        "pct_time_bull": 52.4,
        "pct_time_signal_ok": 36.2,
        "pct_time_eligible": 29.3
      },
      "waterfall": {
        "1_total_bars": 672,
        "2_bull_regime": 352,
        "3_signal_ok": 243,
        "4_eligible": 197,
        "5_not_blocked": 197,
        "6_entries_taken": 9
      },
      "execution_rule_version": "v1_next_open",
      "config_hash": "2e9e399f",
      "regime_qa": {
        "bull_states": [
          1,
          4
        ],
        "bear_state": 0,
        "bull_label_reason": "Bull states: state 1 (occ=20.3%  mean=+0.2115%  std=0.2558%  A_ss=0.549) | state 4 (occ=15.1%  mean=+0.1738%  std=0.7136%  A_ss=0.874)",
        "state_diagnostics": [
          {
            "state": 0,
            "label": "Bear",
            "count_train": 254,
            "pct_train": 15.4,
            "mean_ret_train_pct": -0.2869,
            "std_ret_train_pct": 0.284,
            "model_mean_scaled": -0.4288,
            "A_ss": 0.418
          },
          {
            "state": 1,
            "label": "Bull",
            "count_train": 336,
            "pct_train": 20.3,
            "mean_ret_train_pct": 0.2115,
            "std_ret_train_pct": 0.2558,
            "model_mean_scaled": 0.2819,
            "A_ss": 0.549
          },
          {
            "state": 2,
            "label": "Neutral",
            "count_train": 303,
            "pct_train": 18.3,
            "mean_ret_train_pct": -0.1336,
            "std_ret_train_pct": 1.2528,
            "model_mean_scaled": -0.1985,
            "A_ss": 0.726
          },
          {
            "state": 3,
            "label": "Neutral",
            "count_train": 510,
            "pct_train": 30.9,
            "mean_ret_train_pct": 0.0112,
            "std_ret_train_pct": 0.3903,
            "model_mean_scaled": 0.0127,
            "A_ss": 0.818
          },
          {
            "state": 4,
            "label": "Bull",
            "count_train": 250,
            "pct_train": 15.1,
            "mean_ret_train_pct": 0.1738,
            "std_ret_train_pct": 0.7136,
            "model_mean_scaled": 0.2633,
            "A_ss": 0.874
          }
        ],
        "pct_time_bull_train": 35.5,
        "pct_time_bull_test": 64.6,
        "count_bull_test": 31,
        "total_test_bars": 48
      }
    },
    {
      "Fold": 2,
      "Train Start": "2024-05-18",
      "Train End": "2025-05-18",
      "Test Start": "2025-05-18",
      "Test End": "2025-06-15",
      "_train_end_ts": "2025-05-18 00:00:00+00:00",
      "_test_start_ts": "2025-05-18 01:00:00+00:00",
      "Trades": 6,
      "Total Return (%)": 3.7,
      "Win Rate (%)": 66.67,
      "Max Drawdown (%)": -2.91,
      "Sharpe Ratio": 2.418,
      "Total Fees ($)": 40.42,
      "attribution": {
        "bars_bull_regime": 201,
        "bars_signal_ok_while_bull": 135,
        "bars_eligible": 98,
        "entries_blocked_cooldown": 26,
        "entries_blocked_gate": 0,
        "entries_blocked_external": 0,
        "exits_stop_loss": 1,
        "exits_trailing_stop": 3,
        "exits_take_profit": 1,
        "exits_regime_flip": 1,
        "exits_end_of_data": 0,
        "exits_force_flat": 0,
        "exits_kill_switch": 0,
        "pct_time_bull": 29.9,
        "pct_time_signal_ok": 20.1,
        "pct_time_eligible": 14.6
      },
      "waterfall": {
        "1_total_bars": 672,
        "2_bull_regime": 201,
        "3_signal_ok": 135,
        "4_eligible": 98,
        "5_not_blocked": 98,
        "6_entries_taken": 6
      },
      "execution_rule_version": "v1_next_open",
      "config_hash": "2e9e399f",
      "regime_qa": {
        "bull_states": [
          4
        ],
        "bear_state": 0,
        "bull_label_reason": "Bull states: state 4 (occ=17.0%  mean=+0.5857%  std=0.5298%  A_ss=0.484)",
        "state_diagnostics": [
          {
            "state": 0,
            "label": "Bear",
            "count_train": 204,
            "pct_train": 12.8,
            "mean_ret_train_pct": -0.6536,
            "std_ret_train_pct": 0.5217,
            "model_mean_scaled": -0.9233,
            "A_ss": 0.346
          },
          {
            "state": 1,
            "label": "Neutral",
            "count_train": 517,
            "pct_train": 32.5,
            "mean_ret_train_pct": -0.0157,
            "std_ret_train_pct": 0.3435,
            "model_mean_scaled": -0.036,
            "A_ss": 0.832
          },
          {
            "state": 2,
            "label": "Neutral",
            "count_train": 394,
            "pct_train": 24.7,
            "mean_ret_train_pct": 0.0397,
            "std_ret_train_pct": 0.2412,
            "model_mean_scaled": 0.0599,
            "A_ss": 0.799
          },
          {
            "state": 3,
            "label": "Neutral",
            "count_train": 207,
            "pct_train": 13.0,
            "mean_ret_train_pct": -0.1086,
            "std_ret_train_pct": 1.2799,
            "model_mean_scaled": -0.143,
            "A_ss": 0.69
          },
          {
            "state": 4,
            "label": "Bull",
            "count_train": 271,
            "pct_train": 17.0,
            "mean_ret_train_pct": 0.5857,
            "std_ret_train_pct": 0.5298,
            "model_mean_scaled": 0.7819,
            "A_ss": 0.484
          }
        ],
        "pct_time_bull_train": 17.0,
        "pct_time_bull_test": 22.9,
        "count_bull_test": 8,
        "total_test_bars": 35
      }
    },
    {
      "Fold": 3,
      "Train Start": "2024-06-15",
      "Train End": "2025-06-15",
      "Test Start": "2025-06-15",
      "Test End": "2025-07-13",
      "_train_end_ts": "2025-06-15 00:00:00+00:00",
      "_test_start_ts": "2025-06-15 01:00:00+00:00",
      "Trades": 1,
      "Total Return (%)": 0.21,
      "Win Rate (%)": 100.0,
      "Max Drawdown (%)": -1.13,
      "Sharpe Ratio": 0.529,
      "Total Fees ($)": 8.75,
      "attribution": {
        "bars_bull_regime": 48,
        "bars_signal_ok_while_bull": 40,
        "bars_eligible": 38,
        "entries_blocked_cooldown": 0,
        "entries_blocked_gate": 0,
        "entries_blocked_external": 0,
        "exits_stop_loss": 0,
        "exits_trailing_stop": 0,
        "exits_take_profit": 0,
        "exits_regime_flip": 0,
        "exits_end_of_data": 1,
        "exits_force_flat": 0,
        "exits_kill_switch": 0,
        "pct_time_bull": 7.1,
        "pct_time_signal_ok": 6.0,
        "pct_time_eligible": 5.7
      },
      "waterfall": {
        "1_total_bars": 672,
        "2_bull_regime": 48,
        "3_signal_ok": 40,
        "4_eligible": 38,
        "5_not_blocked": 38,
        "6_entries_taken": 1
      },
      "execution_rule_version": "v1_next_open",
      "config_hash": "2e9e399f",
      "regime_qa": {
        "bull_states": [
          0
        ],
        "bear_state": 1,
        "bull_label_reason": "Bull states: state 0 (occ=17.2%  mean=+0.2489%  std=0.7986%  A_ss=0.756)",
        "state_diagnostics": [
          {
            "state": 0,
            "label": "Bull",
            "count_train": 252,
            "pct_train": 17.2,
            "mean_ret_train_pct": 0.2489,
            "std_ret_train_pct": 0.7986,
            "model_mean_scaled": 0.3185,
            "A_ss": 0.756
          },
          {
            "state": 1,
            "label": "Bear",
            "count_train": 335,
            "pct_train": 22.9,
            "mean_ret_train_pct": -0.1373,
            "std_ret_train_pct": 0.5775,
            "model_mean_scaled": -0.1964,
            "A_ss": 0.734
          },
          {
            "state": 2,
            "label": "Neutral",
            "count_train": 143,
            "pct_train": 9.8,
            "mean_ret_train_pct": -0.1348,
            "std_ret_train_pct": 1.547,
            "model_mean_scaled": -0.1539,
            "A_ss": 0.659
          },
          {
            "state": 3,
            "label": "Neutral",
            "count_train": 343,
            "pct_train": 23.5,
            "mean_ret_train_pct": 0.0262,
            "std_ret_train_pct": 0.3655,
            "model_mean_scaled": 0.021,
            "A_ss": 0.825
          },
          {
            "state": 4,
            "label": "Neutral",
            "count_train": 389,
            "pct_train": 26.6,
            "mean_ret_train_pct": 0.0086,
            "std_ret_train_pct": 0.263,
            "model_mean_scaled": 0.0032,
            "A_ss": 0.796
          }
        ],
        "pct_time_bull_train": 17.2,
        "pct_time_bull_test": 28.8,
        "count_bull_test": 15,
        "total_test_bars": 52
      }
    },
    {
      "Fold": 4,
      "Train Start": "2024-07-13",
      "Train End": "2025-07-13",
      "Test Start": "2025-07-13",
      "Test End": "2025-08-10",
      "_train_end_ts": "2025-07-13 00:00:00+00:00",
      "_test_start_ts": "2025-07-13 01:00:00+00:00",
      "Trades": 8,
      "Total Return (%)": 0.67,
      "Win Rate (%)": 50.0,
      "Max Drawdown (%)": -3.87,
      "Sharpe Ratio": 0.559,
      "Total Fees ($)": 59.27,
      "attribution": {
        "bars_bull_regime": 522,
        "bars_signal_ok_while_bull": 321,
        "bars_eligible": 302,
        "entries_blocked_cooldown": 16,
        "entries_blocked_gate": 0,
        "entries_blocked_external": 0,
        "exits_stop_loss": 2,
        "exits_trailing_stop": 3,
        "exits_take_profit": 0,
        "exits_regime_flip": 2,
        "exits_end_of_data": 1,
        "exits_force_flat": 0,
        "exits_kill_switch": 0,
        "pct_time_bull": 77.7,
        "pct_time_signal_ok": 47.8,
        "pct_time_eligible": 44.9
      },
      "waterfall": {
        "1_total_bars": 672,
        "2_bull_regime": 522,
        "3_signal_ok": 321,
        "4_eligible": 302,
        "5_not_blocked": 302,
        "6_entries_taken": 8
      },
      "execution_rule_version": "v1_next_open",
      "config_hash": "2e9e399f",
      "regime_qa": {
        "bull_states": [
          1,
          2
        ],
        "bear_state": 0,
        "bull_label_reason": "Bull states: state 1 (occ=25.6%  mean=+0.2143%  std=0.3587%  A_ss=0.586) | state 2 (occ=12.0%  mean=+0.6565%  std=0.9840%  A_ss=0.500)",
        "state_diagnostics": [
          {
            "state": 0,
            "label": "Bear",
            "count_train": 152,
            "pct_train": 11.0,
            "mean_ret_train_pct": -1.069,
            "std_ret_train_pct": 0.7199,
            "model_mean_scaled": -1.427,
            "A_ss": 0.347
          },
          {
            "state": 1,
            "label": "Bull",
            "count_train": 354,
            "pct_train": 25.6,
            "mean_ret_train_pct": 0.2143,
            "std_ret_train_pct": 0.3587,
            "model_mean_scaled": 0.293,
            "A_ss": 0.586
          },
          {
            "state": 2,
            "label": "Bull",
            "count_train": 166,
            "pct_train": 12.0,
            "mean_ret_train_pct": 0.6565,
            "std_ret_train_pct": 0.984,
            "model_mean_scaled": 0.8517,
            "A_ss": 0.5
          },
          {
            "state": 3,
            "label": "Neutral",
            "count_train": 252,
            "pct_train": 18.2,
            "mean_ret_train_pct": 0.0795,
            "std_ret_train_pct": 0.5686,
            "model_mean_scaled": 0.1052,
            "A_ss": 0.897
          },
          {
            "state": 4,
            "label": "Neutral",
            "count_train": 461,
            "pct_train": 33.3,
            "mean_ret_train_pct": -0.0596,
            "std_ret_train_pct": 0.3108,
            "model_mean_scaled": -0.0997,
            "A_ss": 0.792
          }
        ],
        "pct_time_bull_train": 37.5,
        "pct_time_bull_test": 69.7,
        "count_bull_test": 23,
        "total_test_bars": 33
      }
    },
    {
      "Fold": 5,
      "Train Start": "2024-08-10",
      "Train End": "2025-08-10",
      "Test Start": "2025-08-10",
      "Test End": "2025-09-07",
      "_train_end_ts": "2025-08-10 00:00:00+00:00",
      "_test_start_ts": "2025-08-10 01:00:00+00:00",
      "Trades": 0,
      "Total Return (%)": 0.0,
      "Win Rate (%)": 0,
      "Max Drawdown (%)": 0.0,
      "Sharpe Ratio": 0.0,
      "Total Fees ($)": 0.0,
      "attribution": {
        "bars_bull_regime": 3,
        "bars_signal_ok_while_bull": 2,
        "bars_eligible": 0,
        "entries_blocked_cooldown": 0,
        "entries_blocked_gate": 0,
        "entries_blocked_external": 0,
        "exits_stop_loss": 0,
        "exits_trailing_stop": 0,
        "exits_take_profit": 0,
        "exits_regime_flip": 0,
        "exits_end_of_data": 0,
        "exits_force_flat": 0,
        "exits_kill_switch": 0,
        "pct_time_bull": 0.4,
        "pct_time_signal_ok": 0.3,
        "pct_time_eligible": 0.0
      },
      "waterfall": {
        "1_total_bars": 672,
        "2_bull_regime": 3,
        "3_signal_ok": 2,
        "4_eligible": 0,
        "5_not_blocked": 0,
        "6_entries_taken": 0
      },
      "execution_rule_version": "v1_next_open",
      "config_hash": "2e9e399f",
      "regime_qa": {
        "bull_states": [
          1,
          2
        ],
        "bear_state": 0,
        "bull_label_reason": "Bull states: state 1 (occ=17.7%  mean=+0.4671%  std=0.7113%  A_ss=0.613) | state 2 (occ=16.8%  mean=+0.2053%  std=0.7601%  A_ss=0.795)",
        "state_diagnostics": [
          {
            "state": 0,
            "label": "Bear",
            "count_train": 157,
            "pct_train": 12.1,
            "mean_ret_train_pct": -0.8571,
            "std_ret_train_pct": 0.7627,
            "model_mean_scaled": -1.2349,
            "A_ss": 0.352
          },
          {
            "state": 1,
            "label": "Bull",
            "count_train": 230,
            "pct_train": 17.7,
            "mean_ret_train_pct": 0.4671,
            "std_ret_train_pct": 0.7113,
            "model_mean_scaled": 0.6645,
            "A_ss": 0.613
          },
          {
            "state": 2,
            "label": "Bull",
            "count_train": 218,
            "pct_train": 16.8,
            "mean_ret_train_pct": 0.2053,
            "std_ret_train_pct": 0.7601,
            "model_mean_scaled": 0.2723,
            "A_ss": 0.795
          },
          {
            "state": 3,
            "label": "Neutral",
            "count_train": 371,
            "pct_train": 28.6,
            "mean_ret_train_pct": -0.009,
            "std_ret_train_pct": 0.2898,
            "model_mean_scaled": -0.0218,
            "A_ss": 0.817
          },
          {
            "state": 4,
            "label": "Neutral",
            "count_train": 322,
            "pct_train": 24.8,
            "mean_ret_train_pct": 0.0085,
            "std_ret_train_pct": 0.3576,
            "model_mean_scaled": -0.0042,
            "A_ss": 0.81
          }
        ],
        "pct_time_bull_train": 34.5,
        "pct_time_bull_test": 10.0,
        "count_bull_test": 3,
        "total_test_bars": 30
      }
    },
    {
      "Fold": 6,
      "Train Start": "2024-09-07",
      "Train End": "2025-09-07",
      "Test Start": "2025-09-07",
      "Test End": "2025-10-05",
      "_train_end_ts": "2025-09-07 00:00:00+00:00",
      "_test_start_ts": "2025-09-07 01:00:00+00:00",
      "Trades": 0,
      "Total Return (%)": 0.0,
      "Win Rate (%)": 0,
      "Max Drawdown (%)": 0.0,
      "Sharpe Ratio": 0.0,
      "Total Fees ($)": 0.0,
      "attribution": {
        "bars_bull_regime": 1,
        "bars_signal_ok_while_bull": 1,
        "bars_eligible": 0,
        "entries_blocked_cooldown": 0,
        "entries_blocked_gate": 0,
        "entries_blocked_external": 0,
        "exits_stop_loss": 0,
        "exits_trailing_stop": 0,
        "exits_take_profit": 0,
        "exits_regime_flip": 0,
        "exits_end_of_data": 0,
        "exits_force_flat": 0,
        "exits_kill_switch": 0,
        "pct_time_bull": 0.1,
        "pct_time_signal_ok": 0.1,
        "pct_time_eligible": 0.0
      },
      "waterfall": {
        "1_total_bars": 672,
        "2_bull_regime": 1,
        "3_signal_ok": 1,
        "4_eligible": 0,
        "5_not_blocked": 0,
        "6_entries_taken": 0
      },
      "execution_rule_version": "v1_next_open",
      "config_hash": "2e9e399f",
      "regime_qa": {
        "bull_states": [
          1,
          2
        ],
        "bear_state": 0,
        "bull_label_reason": "Bull states: state 1 (occ=15.2%  mean=+0.2308%  std=0.7671%  A_ss=0.820) | state 2 (occ=16.1%  mean=+0.5300%  std=0.6985%  A_ss=0.562)",
        "state_diagnostics": [
          {
            "state": 0,
            "label": "Bear",
            "count_train": 102,
            "pct_train": 8.6,
            "mean_ret_train_pct": -1.1827,
            "std_ret_train_pct": 0.6593,
            "model_mean_scaled": -1.6672,
            "A_ss": 0.202
          },
          {
            "state": 1,
            "label": "Bull",
            "count_train": 181,
            "pct_train": 15.2,
            "mean_ret_train_pct": 0.2308,
            "std_ret_train_pct": 0.7671,
            "model_mean_scaled": 0.2976,
            "A_ss": 0.82
          },
          {
            "state": 2,
            "label": "Bull",
            "count_train": 192,
            "pct_train": 16.1,
            "mean_ret_train_pct": 0.53,
            "std_ret_train_pct": 0.6985,
            "model_mean_scaled": 0.7392,
            "A_ss": 0.562
          },
          {
            "state": 3,
            "label": "Neutral",
            "count_train": 342,
            "pct_train": 28.7,
            "mean_ret_train_pct": 0.0006,
            "std_ret_train_pct": 0.3598,
            "model_mean_scaled": -0.0265,
            "A_ss": 0.832
          },
          {
            "state": 4,
            "label": "Neutral",
            "count_train": 374,
            "pct_train": 31.4,
            "mean_ret_train_pct": -0.0032,
            "std_ret_train_pct": 0.3048,
            "model_mean_scaled": -0.0217,
            "A_ss": 0.839
          }
        ],
        "pct_time_bull_train": 31.3,
        "pct_time_bull_test": 1.9,
        "count_bull_test": 1,
        "total_test_bars": 53
      }
    },
    {
      "Fold": 7,
      "Train Start": "2024-10-05",
      "Train End": "2025-10-05",
      "Test Start": "2025-10-05",
      "Test End": "2025-11-02",
      "_train_end_ts": "2025-10-05 00:00:00+00:00",
      "_test_start_ts": "2025-10-05 01:00:00+00:00",
      "Trades": 13,
      "Total Return (%)": -2.82,
      "Win Rate (%)": 53.85,
      "Max Drawdown (%)": -6.34,
      "Sharpe Ratio": -1.619,
      "Total Fees ($)": 94.07,
      "attribution": {
        "bars_bull_regime": 580,
        "bars_signal_ok_while_bull": 339,
        "bars_eligible": 307,
        "entries_blocked_cooldown": 17,
        "entries_blocked_gate": 8,
        "entries_blocked_external": 0,
        "exits_stop_loss": 6,
        "exits_trailing_stop": 4,
        "exits_take_profit": 1,
        "exits_regime_flip": 1,
        "exits_end_of_data": 1,
        "exits_force_flat": 0,
        "exits_kill_switch": 0,
        "pct_time_bull": 86.3,
        "pct_time_signal_ok": 50.4,
        "pct_time_eligible": 45.7
      },
      "waterfall": {
        "1_total_bars": 672,
        "2_bull_regime": 580,
        "3_signal_ok": 339,
        "4_eligible": 307,
        "5_not_blocked": 299,
        "6_entries_taken": 13
      },
      "execution_rule_version": "v1_next_open",
      "config_hash": "2e9e399f",
      "regime_qa": {
        "bull_states": [
          1,
          2,
          3
        ],
        "bear_state": 4,
        "bull_label_reason": "Bull states: state 1 (occ=32.6%  mean=+0.2545%  std=0.2310%  A_ss=0.461) | state 2 (occ=16.5%  mean=+0.5912%  std=0.7167%  A_ss=0.538) | state 3 (occ=14.9%  mean=+0.1129%  std=0.6260%  A_ss=0.884)",
        "state_diagnostics": [
          {
            "state": 0,
            "label": "Neutral",
            "count_train": 295,
            "pct_train": 26.4,
            "mean_ret_train_pct": -0.2956,
            "std_ret_train_pct": 0.2625,
            "model_mean_scaled": -0.4346,
            "A_ss": 0.372
          },
          {
            "state": 1,
            "label": "Bull",
            "count_train": 364,
            "pct_train": 32.6,
            "mean_ret_train_pct": 0.2545,
            "std_ret_train_pct": 0.231,
            "model_mean_scaled": 0.3386,
            "A_ss": 0.461
          },
          {
            "state": 2,
            "label": "Bull",
            "count_train": 184,
            "pct_train": 16.5,
            "mean_ret_train_pct": 0.5912,
            "std_ret_train_pct": 0.7167,
            "model_mean_scaled": 0.8012,
            "A_ss": 0.538
          },
          {
            "state": 3,
            "label": "Bull",
            "count_train": 166,
            "pct_train": 14.9,
            "mean_ret_train_pct": 0.1129,
            "std_ret_train_pct": 0.626,
            "model_mean_scaled": 0.1287,
            "A_ss": 0.884
          },
          {
            "state": 4,
            "label": "Bear",
            "count_train": 108,
            "pct_train": 9.7,
            "mean_ret_train_pct": -1.0519,
            "std_ret_train_pct": 0.7301,
            "model_mean_scaled": -1.5161,
            "A_ss": 0.317
          }
        ],
        "pct_time_bull_train": 63.9,
        "pct_time_bull_test": 62.5,
        "count_bull_test": 55,
        "total_test_bars": 88
      }
    }
  ],
  "lockbox_metrics": {
    "Total Return (%)": -11.25,
    "Buy & Hold Return (%)": -36.19,
    "Alpha (%)": 24.94,
    "Win Rate (%)": 30.77,
    "Max Drawdown (%)": -12.43,
    "Sharpe Ratio": -3.124,
    "Sortino Ratio": -1.189,
    "CVaR 95% (ann %)": -32.378,
    "Max Consec Losses": 4,
    "Max Consec Wins": 2,
    "Worst Decile Trade (%)": -2.19,
    "Large Loss Trades": 0,
    "Time-to-Recovery (h)": null,
    "Total Trades": 26,
    "Stop Loss Exits": 3,
    "Take Profit Exits": 0,
    "Regime Flip Exits": 3,
    "Min Regime Bars": 2,
    "Final Equity ($)": 8874.66,
    "Starting Capital ($)": 10000.0,
    "Total Fees ($)": 206.06,
    "Exit Mode": "Fixed %",
    "Stop Loss (%)": -2.5,
    "Take Profit (%)": 4.0,
    "Fee (bps/side)": 5,
    "Slippage (bps/side)": 3,
    "attribution": {
      "bars_bull_regime": 1127,
      "bars_signal_ok_while_bull": 626,
      "bars_eligible": 434,
      "entries_blocked_cooldown": 137,
      "entries_blocked_gate": 279,
      "entries_blocked_external": 0,
      "exits_stop_loss": 3,
      "exits_trailing_stop": 2,
      "exits_take_profit": 0,
      "exits_regime_flip": 3,
      "exits_end_of_data": 0,
      "exits_force_flat": 0,
      "exits_kill_switch": 18,
      "pct_time_bull": 46.8,
      "pct_time_signal_ok": 26.0,
      "pct_time_eligible": 18.0
    },
    "waterfall": {
      "1_total_bars": 2410,
      "2_bull_regime": 1127,
      "3_signal_ok": 626,
      "4_eligible": 434,
      "5_not_blocked": 155,
      "6_entries_taken": 26
    },
    "execution_rule_version": "v1_next_open",
    "config_hash": "2e9e399f",
    "exits_stop_loss": 3,
    "exits_trailing_stop": 2,
    "exits_take_profit": 0,
    "exits_regime_flip": 3,
    "exits_force_flat": 0,
    "exits_kill_switch": 18,
    "entries_blocked_gate": 279,
    "entries_blocked_external": 0,
    "Period Start": "2025-11-10",
    "Period End": "2026-02-19"
  }
}